[{"ClassId":1,"TaxonId":53385,"ClassValue":"Ungefährdet (*)"},{"ClassId":1,"TaxonId":53722,"ClassValue":"Ungefährdet (*)"},{"ClassId":2,"TaxonId":53629,"ClassValue":"Nicht bewertet"},{"ClassId":1,"TaxonId":53697,"ClassValue":"Ungefährdet (*)"},{"ClassId":1,"TaxonId":53393,"ClassValue":"Ungefährdet (*)"},{"ClassId":1,"TaxonId":53502,"ClassValue":"Ungefährdet (*)"},{"ClassId":3,"TaxonId":53710,"ClassValue":"Extrem Selten (R)"},{"ClassId":3,"TaxonId":53676,"ClassValue":"Extrem Selten (R)"},{"ClassId":2,"TaxonId":53664,"ClassValue":"Nicht bewertet"},{"ClassId":1,"TaxonId":53429,"ClassValue":"Ungefährdet (*)"},{"ClassId":3,"TaxonId":53383,"ClassValue":"Extrem Selten (R)"},{"ClassId":1,"TaxonId":53426,"ClassValue":"Ungefährdet (*)"},{"ClassId":1,"TaxonId":53376,"ClassValue":"Ungefährdet (*)"},{"ClassId":2,"TaxonId":53510,"ClassValue":"Nicht bewertet"},{"ClassId":1,"TaxonId":53430,"ClassValue":"Ungefährdet (*)"},{"ClassId":1,"TaxonId":53665,"ClassValue":"Ungefährdet (*)"},{"ClassId":4,"TaxonId":53736,"ClassValue":"Daten unzureichend (D)"},{"ClassId":2,"TaxonId":53603,"ClassValue":"Nicht bewertet"},{"ClassId":1,"TaxonId":53382,"ClassValue":"Ungefährdet (*)"},{"ClassId":3,"TaxonId":53362,"ClassValue":"Extrem Selten (R)"},{"ClassId":1,"TaxonId":53360,"ClassValue":"Ungefährdet (*)"},{"ClassId":1,"TaxonId":53424,"ClassValue":"Ungefährdet (*)"},{"ClassId":1,"TaxonId":53599,"ClassValue":"Ungefährdet (*)"},{"ClassId":1,"TaxonId":53349,"ClassValue":"Ungefährdet (*)"},{"ClassId":1,"TaxonId":53367,"ClassValue":"Ungefährdet (*)"},{"ClassId":1,"TaxonId":53428,"ClassValue":"Ungefährdet (*)"},{"ClassId":1,"TaxonId":53626,"ClassValue":"Ungefährdet (*)"},{"ClassId":1,"TaxonId":53521,"ClassValue":"Ungefährdet (*)"},{"ClassId":3,"TaxonId":53352,"ClassValue":"Extrem Selten (R)"},{"ClassId":1,"TaxonId":53488,"ClassValue":"Ungefährdet (*)"},{"ClassId":3,"TaxonId":53370,"ClassValue":"Extrem Selten (R)"},{"ClassId":1,"TaxonId":53580,"ClassValue":"Ungefährdet (*)"},{"ClassId":1,"TaxonId":53481,"ClassValue":"Ungefährdet (*)"},{"ClassId":4,"TaxonId":53587,"ClassValue":"Daten unzureichend (D)"},{"ClassId":4,"TaxonId":53586,"ClassValue":"Daten unzureichend (D)"},{"ClassId":1,"TaxonId":53508,"ClassValue":"Ungefährdet (*)"},{"ClassId":4,"TaxonId":53724,"ClassValue":"Daten unzureichend (D)"},{"ClassId":3,"TaxonId":53667,"ClassValue":"Extrem Selten (R)"},{"ClassId":1,"TaxonId":53714,"ClassValue":"Ungefährdet (*)"},{"ClassId":1,"TaxonId":53363,"ClassValue":"Ungefährdet (*)"},{"ClassId":1,"TaxonId":53581,"ClassValue":"Ungefährdet (*)"},{"ClassId":1,"TaxonId":53517,"ClassValue":"Ungefährdet (*)"},{"ClassId":1,"TaxonId":53732,"ClassValue":"Ungefährdet (*)"},{"ClassId":1,"TaxonId":53590,"ClassValue":"Ungefährdet (*)"},{"ClassId":1,"TaxonId":53617,"ClassValue":"Ungefährdet (*)"},{"ClassId":1,"TaxonId":53476,"ClassValue":"Ungefährdet (*)"},{"ClassId":1,"TaxonId":53372,"ClassValue":"Ungefährdet (*)"},{"ClassId":1,"TaxonId":53595,"ClassValue":"Ungefährdet (*)"},{"ClassId":1,"TaxonId":53512,"ClassValue":"Ungefährdet (*)"},{"ClassId":1,"TaxonId":53394,"ClassValue":"Ungefährdet (*)"},{"ClassId":1,"TaxonId":53507,"ClassValue":"Ungefährdet (*)"},{"ClassId":1,"TaxonId":53699,"ClassValue":"Ungefährdet (*)"},{"ClassId":4,"TaxonId":53683,"ClassValue":"Daten unzureichend (D)"},{"ClassId":1,"TaxonId":53485,"ClassValue":"Ungefährdet (*)"},{"ClassId":1,"TaxonId":53350,"ClassValue":"Ungefährdet (*)"},{"ClassId":4,"TaxonId":53596,"ClassValue":"Daten unzureichend (D)"},{"ClassId":1,"TaxonId":53673,"ClassValue":"Ungefährdet (*)"},{"ClassId":1,"TaxonId":53519,"ClassValue":"Ungefährdet (*)"},{"ClassId":2,"TaxonId":53477,"ClassValue":"Nicht bewertet"},{"ClassId":3,"TaxonId":53680,"ClassValue":"Extrem Selten (R)"},{"ClassId":4,"TaxonId":53685,"ClassValue":"Daten unzureichend (D)"},{"ClassId":1,"TaxonId":53348,"ClassValue":"Ungefährdet (*)"},{"ClassId":1,"TaxonId":53730,"ClassValue":"Ungefährdet (*)"},{"ClassId":1,"TaxonId":53616,"ClassValue":"Ungefährdet (*)"},{"ClassId":1,"TaxonId":53514,"ClassValue":"Ungefährdet (*)"},{"ClassId":2,"TaxonId":53630,"ClassValue":"Nicht bewertet"},{"ClassId":1,"TaxonId":53583,"ClassValue":"Ungefährdet (*)"},{"ClassId":4,"TaxonId":53592,"ClassValue":"Daten unzureichend (D)"},{"ClassId":2,"TaxonId":53604,"ClassValue":"Nicht bewertet"},{"ClassId":1,"TaxonId":53721,"ClassValue":"Ungefährdet (*)"},{"ClassId":1,"TaxonId":53351,"ClassValue":"Ungefährdet (*)"},{"ClassId":4,"TaxonId":53527,"ClassValue":"Daten unzureichend (D)"},{"ClassId":1,"TaxonId":53501,"ClassValue":"Ungefährdet (*)"},{"ClassId":3,"TaxonId":53522,"ClassValue":"Extrem Selten (R)"},{"ClassId":1,"TaxonId":53495,"ClassValue":"Ungefährdet (*)"},{"ClassId":1,"TaxonId":53713,"ClassValue":"Ungefährdet (*)"},{"ClassId":4,"TaxonId":53497,"ClassValue":"Daten unzureichend (D)"},{"ClassId":1,"TaxonId":53487,"ClassValue":"Ungefährdet (*)"},{"ClassId":1,"TaxonId":53709,"ClassValue":"Ungefährdet (*)"},{"ClassId":1,"TaxonId":53598,"ClassValue":"Ungefährdet (*)"},{"ClassId":1,"TaxonId":53513,"ClassValue":"Ungefährdet (*)"},{"ClassId":5,"TaxonId":53381,"ClassValue":"Gefährdung unbekannten Ausmaßes (G)"},{"ClassId":1,"TaxonId":53516,"ClassValue":"Ungefährdet (*)"},{"ClassId":1,"TaxonId":53493,"ClassValue":"Ungefährdet (*)"},{"ClassId":2,"TaxonId":53669,"ClassValue":"Nicht bewertet"},{"ClassId":1,"TaxonId":53691,"ClassValue":"Ungefährdet (*)"},{"ClassId":1,"TaxonId":53671,"ClassValue":"Ungefährdet (*)"},{"ClassId":1,"TaxonId":53678,"ClassValue":"Ungefährdet (*)"},{"ClassId":1,"TaxonId":53353,"ClassValue":"Ungefährdet (*)"},{"ClassId":1,"TaxonId":53720,"ClassValue":"Ungefährdet (*)"},{"ClassId":1,"TaxonId":53490,"ClassValue":"Ungefährdet (*)"},{"ClassId":1,"TaxonId":53380,"ClassValue":"Ungefährdet (*)"},{"ClassId":1,"TaxonId":53588,"ClassValue":"Ungefährdet (*)"},{"ClassId":3,"TaxonId":53368,"ClassValue":"Extrem Selten (R)"},{"ClassId":1,"TaxonId":53526,"ClassValue":"Ungefährdet (*)"},{"ClassId":1,"TaxonId":53719,"ClassValue":"Ungefährdet (*)"},{"ClassId":1,"TaxonId":53416,"ClassValue":"Ungefährdet (*)"},{"ClassId":1,"TaxonId":53717,"ClassValue":"Ungefährdet (*)"},{"ClassId":1,"TaxonId":53432,"ClassValue":"Ungefährdet (*)"},{"ClassId":3,"TaxonId":53677,"ClassValue":"Extrem Selten (R)"},{"ClassId":3,"TaxonId":53484,"ClassValue":"Extrem Selten (R)"},{"ClassId":1,"TaxonId":53696,"ClassValue":"Ungefährdet (*)"},{"ClassId":4,"TaxonId":53601,"ClassValue":"Daten unzureichend (D)"},{"ClassId":4,"TaxonId":53690,"ClassValue":"Daten unzureichend (D)"},{"ClassId":3,"TaxonId":53390,"ClassValue":"Extrem Selten (R)"},{"ClassId":2,"TaxonId":53619,"ClassValue":"Nicht bewertet"},{"ClassId":1,"TaxonId":53478,"ClassValue":"Ungefährdet (*)"},{"ClassId":1,"TaxonId":53373,"ClassValue":"Ungefährdet (*)"},{"ClassId":1,"TaxonId":53733,"ClassValue":"Ungefährdet (*)"},{"ClassId":3,"TaxonId":53672,"ClassValue":"Extrem Selten (R)"},{"ClassId":2,"TaxonId":53631,"ClassValue":"Nicht bewertet"},{"ClassId":1,"TaxonId":53371,"ClassValue":"Ungefährdet (*)"},{"ClassId":1,"TaxonId":53499,"ClassValue":"Ungefährdet (*)"},{"ClassId":3,"TaxonId":53369,"ClassValue":"Extrem Selten (R)"},{"ClassId":3,"TaxonId":53698,"ClassValue":"Extrem Selten (R)"},{"ClassId":1,"TaxonId":53524,"ClassValue":"Ungefährdet (*)"},{"ClassId":1,"TaxonId":53486,"ClassValue":"Ungefährdet (*)"},{"ClassId":1,"TaxonId":53491,"ClassValue":"Ungefährdet (*)"},{"ClassId":1,"TaxonId":53425,"ClassValue":"Ungefährdet (*)"},{"ClassId":2,"TaxonId":53356,"ClassValue":"Nicht bewertet"},{"ClassId":3,"TaxonId":53675,"ClassValue":"Extrem Selten (R)"},{"ClassId":1,"TaxonId":53728,"ClassValue":"Ungefährdet (*)"},{"ClassId":4,"TaxonId":53436,"ClassValue":"Daten unzureichend (D)"},{"ClassId":1,"TaxonId":53379,"ClassValue":"Ungefährdet (*)"},{"ClassId":1,"TaxonId":53687,"ClassValue":"Ungefährdet (*)"},{"ClassId":3,"TaxonId":53666,"ClassValue":"Extrem Selten (R)"},{"ClassId":1,"TaxonId":53621,"ClassValue":"Ungefährdet (*)"},{"ClassId":3,"TaxonId":53364,"ClassValue":"Extrem Selten (R)"},{"ClassId":1,"TaxonId":53361,"ClassValue":"Ungefährdet (*)"},{"ClassId":1,"TaxonId":53315,"ClassValue":"Ungefährdet (*)"},{"ClassId":1,"TaxonId":53700,"ClassValue":"Ungefährdet (*)"},{"ClassId":1,"TaxonId":53387,"ClassValue":"Ungefährdet (*)"},{"ClassId":2,"TaxonId":53384,"ClassValue":"Nicht bewertet"},{"ClassId":1,"TaxonId":53670,"ClassValue":"Ungefährdet (*)"},{"ClassId":1,"TaxonId":53682,"ClassValue":"Ungefährdet (*)"},{"ClassId":1,"TaxonId":53725,"ClassValue":"Ungefährdet (*)"},{"ClassId":1,"TaxonId":53311,"ClassValue":"Ungefährdet (*)"},{"ClassId":1,"TaxonId":53701,"ClassValue":"Ungefährdet (*)"},{"ClassId":1,"TaxonId":53500,"ClassValue":"Ungefährdet (*)"},{"ClassId":1,"TaxonId":53729,"ClassValue":"Ungefährdet (*)"},{"ClassId":1,"TaxonId":53391,"ClassValue":"Ungefährdet (*)"},{"ClassId":1,"TaxonId":53374,"ClassValue":"Ungefährdet (*)"},{"ClassId":2,"TaxonId":53354,"ClassValue":"Nicht bewertet"},{"ClassId":1,"TaxonId":53494,"ClassValue":"Ungefährdet (*)"},{"ClassId":1,"TaxonId":53591,"ClassValue":"Ungefährdet (*)"},{"ClassId":4,"TaxonId":53737,"ClassValue":"Daten unzureichend (D)"},{"ClassId":1,"TaxonId":53726,"ClassValue":"Ungefährdet (*)"},{"ClassId":2,"TaxonId":53627,"ClassValue":"Nicht bewertet"},{"ClassId":3,"TaxonId":53437,"ClassValue":"Extrem Selten (R)"},{"ClassId":2,"TaxonId":53358,"ClassValue":"Nicht bewertet"},{"ClassId":1,"TaxonId":53694,"ClassValue":"Ungefährdet (*)"},{"ClassId":1,"TaxonId":53734,"ClassValue":"Ungefährdet (*)"},{"ClassId":1,"TaxonId":53731,"ClassValue":"Ungefährdet (*)"},{"ClassId":3,"TaxonId":53735,"ClassValue":"Extrem Selten (R)"},{"ClassId":2,"TaxonId":53520,"ClassValue":"Nicht bewertet"},{"ClassId":3,"TaxonId":53375,"ClassValue":"Extrem Selten (R)"},{"ClassId":1,"TaxonId":53366,"ClassValue":"Ungefährdet (*)"},{"ClassId":1,"TaxonId":53314,"ClassValue":"Ungefährdet (*)"},{"ClassId":1,"TaxonId":53623,"ClassValue":"Ungefährdet (*)"},{"ClassId":1,"TaxonId":53668,"ClassValue":"Ungefährdet (*)"},{"ClassId":3,"TaxonId":53438,"ClassValue":"Extrem Selten (R)"},{"ClassId":1,"TaxonId":53355,"ClassValue":"Ungefährdet (*)"},{"ClassId":1,"TaxonId":53482,"ClassValue":"Ungefährdet (*)"},{"ClassId":2,"TaxonId":53316,"ClassValue":"Nicht bewertet"},{"ClassId":1,"TaxonId":53684,"ClassValue":"Ungefährdet (*)"},{"ClassId":5,"TaxonId":53594,"ClassValue":"Gefährdung unbekannten Ausmaßes (G)"},{"ClassId":4,"TaxonId":53589,"ClassValue":"Daten unzureichend (D)"},{"ClassId":2,"TaxonId":53622,"ClassValue":"Nicht bewertet"},{"ClassId":1,"TaxonId":53584,"ClassValue":"Ungefährdet (*)"},{"ClassId":1,"TaxonId":53417,"ClassValue":"Ungefährdet (*)"},{"ClassId":3,"TaxonId":53523,"ClassValue":"Extrem Selten (R)"},{"ClassId":1,"TaxonId":53738,"ClassValue":"Ungefährdet (*)"},{"ClassId":1,"TaxonId":53593,"ClassValue":"Ungefährdet (*)"},{"ClassId":1,"TaxonId":53739,"ClassValue":"Ungefährdet (*)"},{"ClassId":1,"TaxonId":53359,"ClassValue":"Ungefährdet (*)"},{"ClassId":3,"TaxonId":53492,"ClassValue":"Extrem Selten (R)"},{"ClassId":1,"TaxonId":53674,"ClassValue":"Ungefährdet (*)"},{"ClassId":2,"TaxonId":53600,"ClassValue":"Nicht bewertet"},{"ClassId":3,"TaxonId":53357,"ClassValue":"Extrem Selten (R)"},{"ClassId":2,"TaxonId":53689,"ClassValue":"Nicht bewertet"},{"ClassId":1,"TaxonId":53435,"ClassValue":"Ungefährdet (*)"},{"ClassId":1,"TaxonId":53625,"ClassValue":"Ungefährdet (*)"},{"ClassId":1,"TaxonId":53480,"ClassValue":"Ungefährdet (*)"},{"ClassId":1,"TaxonId":53688,"ClassValue":"Ungefährdet (*)"},{"ClassId":1,"TaxonId":53679,"ClassValue":"Ungefährdet (*)"},{"ClassId":3,"TaxonId":53496,"ClassValue":"Extrem Selten (R)"},{"ClassId":3,"TaxonId":53386,"ClassValue":"Extrem Selten (R)"},{"ClassId":1,"TaxonId":53693,"ClassValue":"Ungefährdet (*)"},{"ClassId":1,"TaxonId":53715,"ClassValue":"Ungefährdet (*)"},{"ClassId":3,"TaxonId":53585,"ClassValue":"Extrem Selten (R)"},{"ClassId":4,"TaxonId":53723,"ClassValue":"Daten unzureichend (D)"},{"ClassId":1,"TaxonId":53692,"ClassValue":"Ungefährdet (*)"},{"ClassId":1,"TaxonId":53597,"ClassValue":"Ungefährdet (*)"},{"ClassId":1,"TaxonId":53433,"ClassValue":"Ungefährdet (*)"},{"ClassId":1,"TaxonId":53388,"ClassValue":"Ungefährdet (*)"},{"ClassId":5,"TaxonId":53378,"ClassValue":"Gefährdung unbekannten Ausmaßes (G)"},{"ClassId":2,"TaxonId":53504,"ClassValue":"Nicht bewertet"},{"ClassId":1,"TaxonId":53740,"ClassValue":"Ungefährdet (*)"},{"ClassId":3,"TaxonId":53434,"ClassValue":"Extrem Selten (R)"},{"ClassId":2,"TaxonId":53503,"ClassValue":"Nicht bewertet"},{"ClassId":4,"TaxonId":53377,"ClassValue":"Daten unzureichend (D)"},{"ClassId":2,"TaxonId":53317,"ClassValue":"Nicht bewertet"},{"ClassId":4,"TaxonId":53716,"ClassValue":"Daten unzureichend (D)"},{"ClassId":4,"TaxonId":53708,"ClassValue":"Daten unzureichend (D)"},{"ClassId":1,"TaxonId":53525,"ClassValue":"Ungefährdet (*)"},{"ClassId":4,"TaxonId":53511,"ClassValue":"Daten unzureichend (D)"},{"ClassId":1,"TaxonId":53489,"ClassValue":"Ungefährdet (*)"},{"ClassId":1,"TaxonId":53620,"ClassValue":"Ungefährdet (*)"},{"ClassId":1,"TaxonId":53632,"ClassValue":"Ungefährdet (*)"},{"ClassId":4,"TaxonId":53392,"ClassValue":"Daten unzureichend (D)"},{"ClassId":1,"TaxonId":53727,"ClassValue":"Ungefährdet (*)"},{"ClassId":2,"TaxonId":53618,"ClassValue":"Nicht bewertet"},{"ClassId":1,"TaxonId":53365,"ClassValue":"Ungefährdet (*)"},{"ClassId":1,"TaxonId":53681,"ClassValue":"Ungefährdet (*)"},{"ClassId":4,"TaxonId":53475,"ClassValue":"Daten unzureichend (D)"},{"ClassId":1,"TaxonId":53718,"ClassValue":"Ungefährdet (*)"},{"ClassId":1,"TaxonId":53695,"ClassValue":"Ungefährdet (*)"}]